pyakri_de_utils/__init__.py
pyakri_de_utils/arrow_utils.py
pyakri_de_utils/common_utils.py
pyakri_de_utils/constants.py
pyakri_de_utils/data_converter_utils.py
pyakri_de_utils/enums.py
pyakri_de_utils/error_prefix_formatter.py
pyakri_de_utils/file_utils.py
pyakri_de_utils/image_utils.py
pyakri_de_utils/logger.py
pyakri_de_utils/numpy_utils.py
pyakri_de_utils/onnx_utils.py
pyakri_de_utils/retry_helper.py
pyakri_de_utils/store_utils.py
pyakri_de_utils/rest/__init__.py
pyakri_de_utils/rest/exceptions.py
pyakri_de_utils/rest/models.py
pyakri_de_utils/rest/requests_session_manager.py
pyakri_de_utils/rest/rest_client.py
pyakri_de_utils/rest/utils.py
pyakri_de_utils-1.25.0.dev0.dist-info/METADATA
pyakri_de_utils-1.25.0.dev0.dist-info/WHEEL
pyakri_de_utils-1.25.0.dev0.dist-info/top_level.txt
pyakri_de_utils-1.25.0.dev0.dist-info/RECORD
